gcp/bigquery.py
gcp/cloudsql.py
gcp/gcs.py
utils/backup.py
utils/mailer.py
utils/slacker.py
utils/yaml2wdl.py
stanford_wdl_kit-1.6.1.dist-info/METADATA
stanford_wdl_kit-1.6.1.dist-info/WHEEL
stanford_wdl_kit-1.6.1.dist-info/entry_points.txt
stanford_wdl_kit-1.6.1.dist-info/namespace_packages.txt
stanford_wdl_kit-1.6.1.dist-info/top_level.txt
stanford_wdl_kit-1.6.1.dist-info/zip-safe
stanford_wdl_kit-1.6.1.dist-info/RECORD
